hangman_solver/__init__.py
hangman_solver/__init__.pyi
hangman_solver/_solver.abi3.so
hangman_solver/py.typed
hangman_solver_rs-0.6.9.dist-info/METADATA
hangman_solver_rs-0.6.9.dist-info/WHEEL
hangman_solver_rs-0.6.9.dist-info/licenses/LICENSE
hangman_solver_rs-0.6.9.dist-info/RECORD
