Metadata-Version: 2.4
Name: hangman-solver-rs
Version: 0.6.9
Classifier: Development Status :: 4 - Beta
Classifier: Intended Audience :: Developers
Classifier: License :: OSI Approved :: European Union Public Licence 1.2 (EUPL 1.2)
Classifier: Operating System :: OS Independent
Classifier: Programming Language :: Rust
Classifier: Topic :: Software Development
Classifier: Topic :: Software Development :: Libraries
Classifier: Typing :: Typed
License-File: LICENSE
License-File: LICENSE
Summary: Solves hangman puzzles
Keywords: hangman,solver,rust
Requires-Python: >=3.12
Project-URL: Source Code, https://github.com/asozialesnetzwerk/hangman_solver
